<?xml version="1.0" encoding="UTF-8" standalone="yes"?>
<ns3:FileMetadati xmlns:ns2="http://www.w3.org/2000/09/xmldsig#" xmlns:ns3="http://ivaservizi.agenziaentrate.gov.it/docs/xsd/fattura/messaggi/v1.0" versione="1.0">
    <IdentificativoSdI>16868522479</IdentificativoSdI>
    <NomeFile>IT0526289001426071_GBF9E.xml.p7m</NomeFile>
    <Hash>1373d22c20f5f4322ff770c3c5198a1b9d2229a0a2261ca6db31c00dd37a1ba3</Hash>
    <CodiceDestinatario>0000000</CodiceDestinatario>
    <Formato>FPR12</Formato>
    <TentativiInvio>1</TentativiInvio>
    <MessageId>40600459479</MessageId>
</ns3:FileMetadati>
